<?xml version="1.0"?>

<model-hints>
	<model name="com.armantec.sms.branch.model.Branch">
		<field name="uuid" type="String" />
		<field name="id" type="long" />
		<field name="groupId" type="long" />
		<field name="companyId" type="long" />
		<field name="userId" type="long" />
		<field name="userName" type="String" />
		<field name="createDate" type="Date" />
		<field name="modifiedDate" type="Date" />
		<field name="deleted" type="boolean" />
		<field name="name" type="String" />
		<field name="code" type="String" />
		<field name="numberOfSeat" type="int" />
	</model>
</model-hints>